GEMATRIA/__init__.py
GEMATRIA/nmf.py
GEMATRIA/plot.py
GEMATRIA/transform.py
MOMIA/__init__.py
MOMIA/boundary.py
MOMIA/cell.py
MOMIA/cluster.py
MOMIA/config.py
MOMIA/helper.py
MOMIA/image.py
MOMIA/io.py
MOMIA/measure.py
MOMIA/metrics.py
MOMIA/plot.py
MOMIA/configurations/__init__.py
MOMIA/configurations/boundary_MLP.pk
MOMIA/configurations/boundary_tree.pk
MOMIA/configurations/configuration_MSR.ini
MOMIA/configurations/configuration_default.ini
MOMIA/configurations/configuration_msm.ini
MOMIA/configurations/configuration_mtb.ini
MOMIA/configurations/normalizer.pk
MOMIA-0.0.1.dist-info/LICENCE
MOMIA-0.0.1.dist-info/METADATA
MOMIA-0.0.1.dist-info/WHEEL
MOMIA-0.0.1.dist-info/top_level.txt
MOMIA-0.0.1.dist-info/RECORD
