Metadata-Version: 2.1
Name: MOMIA
Version: 0.0.1
Summary: Mycobacteria-Optimized Microscopy Image Analysis
Home-page: https://github.com/jzrolling/MOMIA
Author: jz-rolling
Author-email: juzhu@hsph.harvard.edu
License: UNKNOWN
Platform: UNKNOWN
Classifier: Programming Language :: Python :: 3
Classifier: License :: OSI Approved :: MIT License
Classifier: Operating System :: OS Independent
Requires-Python: >=3.7
License-File: LICENCE
